mycalc/calculator.py
yejun230411-1.0.1.dist-info/METADATA
yejun230411-1.0.1.dist-info/WHEEL
yejun230411-1.0.1.dist-info/top_level.txt
yejun230411-1.0.1.dist-info/RECORD
