Metadata-Version: 2.1
Name: yejun230411
Version: 1.0.1
Summary: nice calculator
Home-page: http://github.com/JJun0/abc
Download-URL: http://github.com/JJun0/abc/
Author: kimyejun
License: UNKNOWN
Platform: UNKNOWN
